qubership_pipelines_common_library/__init__.py
qubership_pipelines_common_library/v1/__init__.py
qubership_pipelines_common_library/v1/artifactory_client.py
qubership_pipelines_common_library/v1/execution/__init__.py
qubership_pipelines_common_library/v1/execution/exec_command.py
qubership_pipelines_common_library/v1/execution/exec_context.py
qubership_pipelines_common_library/v1/execution/exec_context_file.py
qubership_pipelines_common_library/v1/execution/exec_info.py
qubership_pipelines_common_library/v1/execution/exec_logger.py
qubership_pipelines_common_library/v1/git_client.py
qubership_pipelines_common_library/v1/github_client.py
qubership_pipelines_common_library/v1/gitlab_client.py
qubership_pipelines_common_library/v1/jenkins_client.py
qubership_pipelines_common_library/v1/kube_client.py
qubership_pipelines_common_library/v1/log_client.py
qubership_pipelines_common_library/v1/minio_client.py
qubership_pipelines_common_library/v1/utils/__init__.py
qubership_pipelines_common_library/v1/utils/rest.py
qubership_pipelines_common_library/v1/utils/utils.py
qubership_pipelines_common_library/v1/utils/utils_cli.py
qubership_pipelines_common_library/v1/utils/utils_context.py
qubership_pipelines_common_library/v1/utils/utils_dictionary.py
qubership_pipelines_common_library/v1/utils/utils_file.py
qubership_pipelines_common_library/v1/utils/utils_json.py
qubership_pipelines_common_library/v1/utils/utils_string.py
qubership_pipelines_common_library/v1/webex_client.py
qubership_pipelines_common_library_py39-0.1.10.dist-info/LICENSE
qubership_pipelines_common_library_py39-0.1.10.dist-info/METADATA
qubership_pipelines_common_library_py39-0.1.10.dist-info/WHEEL
qubership_pipelines_common_library_py39-0.1.10.dist-info/RECORD
