Metadata-Version: 2.3
Name: qubership-pipelines-common-library-py39
Version: 0.1.10
Summary: Qubership Pipelines common library backported for Python 3.9
License: Apache-2.0
Author: Igor Lebedev
Author-email: lebedev.light@gmail.com
Requires-Python: >=3.9,<4.0
Classifier: License :: OSI Approved :: Apache Software License
Classifier: Programming Language :: Python :: 3
Classifier: Programming Language :: Python :: 3.9
Classifier: Programming Language :: Python :: 3.10
Classifier: Programming Language :: Python :: 3.11
Classifier: Programming Language :: Python :: 3.12
Classifier: Programming Language :: Python :: 3.13
Requires-Dist: GitPython (>=3.1.43,<4.0.0)
Requires-Dist: click (>=8.1.7,<9.0.0)
Requires-Dist: ghapi (>=1.0.6,<2.0.0)
Requires-Dist: http-exceptions (>=0.2.10,<0.3.0)
Requires-Dist: kubernetes (>=29.0.0,<30.0.0)
Requires-Dist: minio (>=7.2.12,<8.0.0)
Requires-Dist: python-gitlab (>=4.13.0,<5.0.0)
Requires-Dist: python-jenkins (>=1.8.2,<2.0.0)
Requires-Dist: pyyaml (>=6.0.2,<7.0.0)
Requires-Dist: requests (>=2.32.3,<3.0.0)
Requires-Dist: urllib3 (>=2.2.3,<3.0.0)
